{
    "telemetry.sqmId": "",
    "telemetry.machineId": "938b9396ca9c7a072e3971f6268b7b02cbc2d33e9930cfe69a0887aaeb0dc229",
    "telemetry.devDeviceId": "0a309992-2a9a-4b18-8324-224d0de34f19",
    "backupWorkspaces": {
        "workspaces": [],
        "folders": [
            {
                "folderUri": "file:///home/axel/Documents/py"
            }
        ],
        "emptyWindows": []
    },
    "windowControlHeight": 42,
    "profileAssociations": {
        "workspaces": {
            "file:///home/axel/Documents/py": "__default__profile__"
        },
        "emptyWindows": {}
    },
    "theme": "vs-dark",
    "themeBackground": "#1e1e2e",
    "windowSplash": {
        "zoomLevel": 0,
        "baseTheme": "vs-dark",
        "colorInfo": {
            "foreground": "#cdd6f4",
            "background": "#1e1e2e",
            "editorBackground": "#1e1e2e",
            "titleBarBackground": "#11111b",
            "titleBarBorder": "rgba(0, 0, 0, 0)",
            "activityBarBackground": "#11111b",
            "activityBarBorder": "rgba(0, 0, 0, 0)",
            "sideBarBackground": "#181825",
            "sideBarBorder": "rgba(0, 0, 0, 0)",
            "statusBarBackground": "#11111b",
            "statusBarBorder": "rgba(0, 0, 0, 0)",
            "statusBarNoFolderBackground": "#11111b",
            "windowBorder": "rgba(0, 0, 0, 0)"
        },
        "layoutInfo": {
            "sideBarSide": "left",
            "editorPartMinWidth": 220,
            "titleBarHeight": 35,
            "activityBarWidth": 48,
            "sideBarWidth": 180,
            "auxiliaryBarWidth": 0,
            "statusBarHeight": 22,
            "windowBorder": false
        }
    },
    "windowsState": {
        "lastActiveWindow": {
            "folder": "file:///home/axel/Documents/py",
            "backupPath": "/home/axel/.config/Code/Backups/32916f0cf4a1880edc047e85ec5810d4",
            "uiState": {
                "mode": 1,
                "x": 1285,
                "y": 752,
                "width": 1265,
                "height": 678,
                "zoomLevel": 1
            }
        },
        "openedWindows": []
    },
    "windowSplashWorkspaceOverride": {
        "layoutInfo": {
            "sideBarWidth": 180,
            "auxiliaryBarWidth": 300,
            "workspaces": {
                "b142d5ddcedf55f69a9c9998120ab21f": {
                    "sideBarVisible": true,
                    "auxiliaryBarVisible": false
                }
            }
        }
    }
}